evencheck/__init__.py
evencheck/is_even.py
evencheck-1.5.0.dist-info/licenses/LICENSE
evencheck-1.5.0.dist-info/METADATA
evencheck-1.5.0.dist-info/WHEEL
evencheck-1.5.0.dist-info/top_level.txt
evencheck-1.5.0.dist-info/RECORD
