Metadata-Version: 2.4
Name: evencheck
Version: 1.5.0
Summary: The most inefficient way to check if a number is even.
Author: GussApenas
License: MIT License
Project-URL: Repository, https://github.com/GussApenass/evencheck
Requires-Python: >=3.8
License-File: LICENSE
Requires-Dist: aiohttp
Requires-Dist: aiofiles
Dynamic: license-file
